mathutils/__init__.py
mathutils/arithmetic.py
mathutils/statistics.py
mathutils/vectors.py
arunmoorthy_mathutils-0.1.0.dist-info/LICENSE
arunmoorthy_mathutils-0.1.0.dist-info/METADATA
arunmoorthy_mathutils-0.1.0.dist-info/WHEEL
arunmoorthy_mathutils-0.1.0.dist-info/top_level.txt
arunmoorthy_mathutils-0.1.0.dist-info/RECORD
