Metadata-Version: 2.2
Name: arunmoorthy-mathutils
Version: 0.1.0
Summary: A simple utility package for mathematical operations
Home-page: https://github.com/yourusername/mathutils
Author: Your Name
Author-email: Your Name <your.email@example.com>
License: MIT
Project-URL: Homepage, https://github.com/yourusername/mathutils
Project-URL: Bug Tracker, https://github.com/yourusername/mathutils/issues
Classifier: Programming Language :: Python :: 3
Classifier: License :: OSI Approved :: MIT License
Classifier: Operating System :: OS Independent
Requires-Python: >=3.7
License-File: LICENSE
Dynamic: author
Dynamic: home-page
Dynamic: requires-python
